<?xml version="1.0" encoding="UTF-8"?>

<!DOCTYPE tiles-definitions PUBLIC
       "-//Apache Software Foundation//DTD Tiles Configuration 2.1//EN"
       "http://tiles.apache.org/dtds/tiles-config_2_1.dtd">

<tiles-definitions>

	<definition name="main2" template="/WEB-INF/main/main2.jsp">
		<put-attribute name="title" value="Remedium Hotel[당신만을 위한 오리엔탈 프리미엄 에디션]" />						
		<put-attribute name="header" value="/WEB-INF/main/header.jsp" />		
		<put-attribute name="body" value="/WEB-INF/main/body.jsp" /> 
		<put-attribute name="footer" value="/WEB-INF/main/footer.jsp" />	
		
	</definition>

	<definition name="main3" template="/WEB-INF/main/main3.jsp">
		<put-attribute name="title" value="Remedium Hotel[당신만을 위한 오리엔탈 프리미엄 에디션]" />						
		<put-attribute name="header" value="/WEB-INF/main/header.jsp" />		
		<put-attribute name="body" value="/WEB-INF/main/body.jsp" /> 
		<put-attribute name="footer" value="/WEB-INF/main/footer.jsp" />	
		
	</definition>
	
	
	
	
	<definition name="loginForm" extends="main2">
		<put-attribute name="body" value="/WEB-INF/login/loginForm.jsp" />
	</definition>
	
	<definition name="modifyForm" extends="main2">
		<put-attribute name="body" value="/WEB-INF/login/modifyForm.jsp" />
	</definition>
	
		
	<!-- 회원가입폼 -->
 	<definition name="joinForm" extends="main2">
		<put-attribute name="body" value="/WEB-INF/join/joinForm.jsp" />
	</definition>
	
		
	<!-- 마이 페이지 폼 -->
 	<definition name="mypage" extends="main2">
		<put-attribute name="body" value="/WEB-INF/mypage/pageMain.jsp" />
	</definition>
	
	
 <!-- main -->

<!--
	<definition name="mainForm3" extends="main31">
		<put-attribute name="body" value="/WEB-INF/main/body.jsp" />
	</definition>
	


 -->
 	<!-- Main Page -->
<!-- 	<definition name="default" template="/WEB-INF/views/layout/layout.jsp">
		<put-attribute name="header" value="/WEB-INF/views/layout/header.jsp" />
		<put-attribute name="body" value="/WEB-INF/views/layout/container.jsp" />
		<put-attribute name="footer" value="/WEB-INF/views/layout/footer.jsp" />
	</definition>
	
	<definition name="main" template="/WEB-INF/views/layout/layout_main.jsp">
		<put-attribute name="header" value="/WEB-INF/views/layout/header_main.jsp" />
		<put-attribute name="body" value="/WEB-INF/views/layout/container.jsp" />
		<put-attribute name="footer" value="/WEB-INF/views/layout/footer.jsp" />
	</definition>
	
	<definition name="admin" template="/WEB-INF/views/layout/admin/layout.jsp">
		<put-attribute name="body" value="/WEB-INF/views/layout/admin/container.jsp" />
	</definition>
	
	
	
	<definition name="mainForm" extends="default">
		<put-attribute name="body" value="/WEB-INF/views/layout/main.jsp" />
	</definition>
 -->	

	

	
	
	
</tiles-definitions>
	
	